{
    "prod": {
        "app_function": "run.app",
        "aws_region": "us-east-2",
        "profile_name": null,
        "project_name": "workoutgenerator",
        "runtime": "python3.6",
        "environment_variables": {
            "ENV_SECRET_NAME": "workoutgenerator/secretkey",
            "ENV_SECRET_KEY": "WORKOUT_GEN_KEY",
            "ENV_REGION": "us-east-2",
            "USER_TABLE": "prod-WorkoutGenerator-Users"
        },
        "extra_permissions": [{
            "Effect": "Allow",
            "Action": ["secretsmanager:GetSecretValue"],
            "Resource": "*"
        }],
        "s3_bucket": "zappa-workout-prod",
        "domain": "themcilroy.com",
        "route53_enabled": true,
        "certificate_arn": "arn:aws:acm:us-east-1:824269988929:certificate/fdc01f6c-be49-40b3-afb7-707d085d1042"
    },
    "dev": {
        "app_function": "run.app",
        "aws_region": "us-east-2",
        "profile_name": null,
        "project_name": "workoutgenerator",
        "runtime": "python3.6",
        "environment_variables": {
            "ENV_SECRET_NAME": "workoutgenerator/secretkey",
            "ENV_SECRET_KEY": "WORKOUT_GEN_KEY",
            "ENV_REGION": "us-east-2",
            "USER_TABLE": "dev-WorkoutGenerator-Users"
        },
        "extra_permissions": [{
            "Effect": "Allow",
            "Action": ["secretsmanager:GetSecretValue"],
            "Resource": "*"
        }],
        "s3_bucket": "zappa-workout-dev",
        "domain": "dev.themcilroy.com",
        "route53_enabled": true,
        "certificate_arn": "arn:aws:acm:us-east-1:824269988929:certificate/fdc01f6c-be49-40b3-afb7-707d085d1042"
    }
}
